vinci_lang/__init__.py
vinci_lang/cli.py
vinci_lang-1.0.6.dist-info/LICENSE
vinci_lang-1.0.6.dist-info/METADATA
vinci_lang-1.0.6.dist-info/WHEEL
vinci_lang-1.0.6.dist-info/entry_points.txt
vinci_lang-1.0.6.dist-info/RECORD
