Metadata-Version: 2.3
Name: vinci-lang
Version: 1.0.6
Summary: VINCI is a general purpose programming language that is numbers oriented and retro.
License: MIT
Author: SeafoodStudios
Requires-Python: >=3.11
Classifier: License :: OSI Approved :: MIT License
Classifier: Programming Language :: Python :: 3
Classifier: Programming Language :: Python :: 3.11
Classifier: Programming Language :: Python :: 3.12
Classifier: Programming Language :: Python :: 3.13
